mundi/__init__.py
mundi/__main__.py
mundi/cli.py
mundi/constants.py
mundi/db.py
mundi/extra.py
mundi/fix.py
mundi/functions.py
mundi/loader.py
mundi/pandas.py
mundi/transforms.py
mundi/databases/db.sqlite
mundi/databases/un.pkl.gz
mundi/plugin/__init__.py
mundi/plugin/plugin.py
mundi/plugin/utils.py
mundi/types/__init__.py
mundi/types/region.py
mundi/types/region_plugins.py
mundi/types/typing.py
mundi-0.2.3.dist-info/LICENSE
mundi-0.2.3.dist-info/WHEEL
mundi-0.2.3.dist-info/METADATA
mundi-0.2.3.dist-info/RECORD
