Metadata-Version: 2.1
Name: mundi
Version: 0.2.3
Summary: Centralize data from countries and regions around the World and expose it
Home-page: https://github.com/pydemic/mundi
License: UNKNOWN
Author: Fábio Macêdo Mendes
Author-email: fabiomacedomendes@gmail.com
Classifier: Intended Audience :: Developers
Classifier: Development Status :: 4 - Beta
Classifier: License :: OSI Approved :: MIT License
Classifier: Operating System :: OS Independent
Classifier: Programming Language :: Python
Classifier: Programming Language :: Python :: 3
Classifier: Programming Language :: Python :: 3.6
Classifier: Programming Language :: Python :: 3.7
Classifier: Programming Language :: Python :: 3.8
Classifier: Topic :: Software Development :: Libraries
Requires-Dist: pandas
Requires-Dist: sidekick
Requires-Dist: black ; extra == "dev"
Requires-Dist: twine ; extra == "dev"
Requires-Dist: pycountry ; extra == "dev"
Requires-Dist: coverage~=5.0 ; extra == "dev"
Requires-Dist: pytest~=5.0 ; extra == "dev"
Provides-Extra: dev
